pandas_context/__init__.py
pandas_context/_version.py
pandas_context-0.0.2.dist-info/METADATA
pandas_context-0.0.2.dist-info/WHEEL
pandas_context-0.0.2.dist-info/top_level.txt
pandas_context-0.0.2.dist-info/RECORD
